{"_id":"57d17c5e2459775a5c57d17d","_name":"flashlight_ultrafire_WF-501B","_parent":"55818b084bdc2d5b648b4571","_props":{"AnimationVariantsNumber":0,"BackgroundColor":"blue","BlocksCollapsible":false,"CanPutIntoDuringTheRaid":true,"CanRequireOnRagfair":true,"CanSellOnRagfair":true,"CantRemoveFromSlotsDuringRaid":[],"ConflictingItems":["SPTRM","undefined","0","0","0","0","0","0","0","0","0","0","0","false","0","false","0","0","0","0"],"Description":"flashlight_ultrafire_WF-501B","DiscardLimit":-1,"DiscardingBlock":false,"DoubleActionAccuracyPenaltyMult":1,"DropSoundType":"None","Durability":100,"EffectiveDistance":0,"Ergonomics":0,"ExamineExperience":12,"ExamineTime":0.25,"ExaminedByDefault":true,"ExtraSizeDown":0,"ExtraSizeForceAdd":false,"ExtraSizeLeft":0,"ExtraSizeRight":0,"ExtraSizeUp":0,"Grids":[],"Height":1,"HideEntrails":false,"InsuranceDisabled":false,"IsAlwaysAvailableForInsurance":false,"IsAnimated":false,"IsLockedafterEquip":false,"IsSpecialSlotOnly":false,"IsUnbuyable":false,"IsUndiscardable":false,"IsUngivable":false,"IsUnremovable":false,"IsUnsaleable":false,"ItemSound":"mod","LootExperience":10,"MergesWithChildren":true,"ModesCount":2,"Name":"flashlight_ultrafire_WF-501B","NotShownInSlot":false,"Prefab":{"path":"assets/content/items/mods/flashlights/flashlight_ultrafire_wf-501b.bundle","rcid":""},"QuestItem":false,"QuestStashMaxCount":0,"RagFairCommissionModifier":1,"RaidModdable":true,"Recoil":0,"RepairCost":0,"RepairSpeed":0,"ShortName":"flashlight_ultrafire_WF-501B","SightingRange":0,"Slots":[],"StackMaxSize":1,"StackObjectsCount":1,"ToolModdable":true,"UniqueAnimationModID":0,"Unlootable":false,"UnlootableFromSide":[],"UnlootableFromSlot":"FirstPrimaryWeapon","UsePrefab":{"path":"","rcid":""},"Weight":0.112,"Width":1,"LevelRewardsItemLevel":1},"_type":"Item"}