{"_id":"590c60fc86f77412b13fddcf","_name":"item_info_docbag","_parent":"5795f317245977243854e041","_props":{"AnimationVariantsNumber":0,"BackgroundColor":"blue","CanPutIntoDuringTheRaid":true,"CanRequireOnRagfair":true,"CanSellOnRagfair":true,"CantRemoveFromSlotsDuringRaid":[],"ConflictingItems":[],"Description":"Docbag","DiscardLimit":0,"DiscardingBlock":false,"DropSoundType":"None","ExamineExperience":20,"ExamineTime":0.25,"ExaminedByDefault":true,"ExtraSizeDown":0,"ExtraSizeForceAdd":false,"ExtraSizeLeft":0,"ExtraSizeRight":0,"ExtraSizeUp":0,"Grids":[{"_id":"590c60fc86f77412b13fddd0","_name":"main","_parent":"590c60fc86f77412b13fddcf","_props":{"cellsH":4,"cellsV":4,"filters":[{"ExcludedFilter":[],"Filter":["59faff1d86f7746c51718c9c","5d235b4d86f7742e017bc88a","5f745ee30acaeb0d490d8c5b","619cbf9e0a7c3a1a2731940a","5448ecbe4bdc2d60728b4568","543be5e94bdc2df1348b4568","567849dd4bdc2d150f8b456e","543be5dd4bdc2deb348b4569","RequisitionSlips"]}],"isSortingTable":false,"maxCount":0,"maxWeight":0,"minCount":0},"_proto":"55d329c24bdc2d892f8b4567"}],"Height":2,"HideEntrails":true,"InsuranceDisabled":true,"IsAlwaysAvailableForInsurance":false,"IsLockedafterEquip":false,"IsSpecialSlotOnly":false,"IsUnbuyable":false,"IsUndiscardable":false,"IsUngivable":false,"IsUnremovable":false,"IsUnsaleable":false,"ItemSound":"gear_generic","LootExperience":60,"MergesWithChildren":false,"Name":"Docbag","NotShownInSlot":false,"Prefab":{"path":"assets/content/items/infosubject/item_info_docbag/item_info_docbag.bundle","rcid":""},"QuestItem":false,"QuestStashMaxCount":0,"RagFairCommissionModifier":1,"RepairCost":0,"RepairSpeed":0,"ShortName":"Docbag","Slots":[],"StackMaxSize":1,"StackObjectsCount":1,"TagColor":0,"TagName":"","Unlootable":false,"UnlootableFromSide":[],"UnlootableFromSlot":"FirstPrimaryWeapon","UsePrefab":{"path":"","rcid":""},"Weight":0.82,"Width":1,"LevelRewardsItemLevel":3},"_proto":"577e1c9d2459773cd707c525","_type":"Item"}