{"_id":"5bead2e00db834001c062938","_name":"weapon_voentorg_mpl-40","_parent":"5447e1d04bdc2dff2f8b4567","_props":{"AdditionalAnimationLayer":0,"AnimationVariantsNumber":0,"AppliedHeadRotation":{"x":2,"y":4,"z":0},"AppliedTrunkRotation":{"x":0,"y":0,"z":0},"BackgroundColor":"grey","CanRequireOnRagfair":true,"CanSellOnRagfair":true,"ColliderScaleMultiplier":{"x":1,"y":1,"z":1},"ConflictingItems":[],"DeflectionConsumption":3,"Description":"weapon_voentorg_mpl-50","DiscardLimit":0,"DiscardingBlock":false,"DisplayOnModel":false,"DropSoundType":"None","Durability":65,"ExamineExperience":20,"ExamineTime":0.25,"ExaminedByDefault":true,"ExtraSizeDown":0,"ExtraSizeForceAdd":false,"ExtraSizeLeft":0,"ExtraSizeRight":0,"ExtraSizeUp":0,"Height":3,"HideEntrails":false,"InsuranceDisabled":true,"IsAlwaysAvailableForInsurance":false,"IsLockedafterEquip":false,"IsSpecialSlotOnly":false,"IsUnbuyable":false,"IsUndiscardable":false,"IsUngivable":false,"IsUnremovable":false,"IsUnsaleable":false,"ItemSound":"knife_generic","LootExperience":30,"MaxDurability":65,"MaxRepairDegradation":0.01,"MaxResource":0,"MergesWithChildren":false,"MinRepairDegradation":0,"Name":"weapon_voentorg_mpl-50","NotShownInSlot":false,"Prefab":{"path":"assets/content/weapons/mpl40/weapon_voentorg_mpl-40_container.bundle","rcid":""},"PrimaryConsumption":10,"PrimaryDistance":0.55,"QuestItem":false,"QuestStashMaxCount":0,"RagFairCommissionModifier":1,"RepairCost":0,"RepairSpeed":0,"SecondryConsumption":13,"SecondryDistance":0.65,"ShortName":"weapon_voentorg_mpl-50","SlashPenetration":1,"StabPenetration":1,"StackMaxSize":1,"StackObjectsCount":1,"StaminaBurnRate":0,"StimulatorBuffs":"","Unlootable":true,"UnlootableFromSide":["Bear","Usec"],"UnlootableFromSlot":"Scabbard","UsePrefab":{"path":"","rcid":""},"Weight":0.8,"Width":1,"knifeDurab":65,"knifeHitDelay":0,"knifeHitRadius":0.55,"knifeHitSlashDam":24,"knifeHitSlashRate":0,"knifeHitStabDam":43,"knifeHitStabRate":1,"LevelRewardsItemLevel":5},"_proto":"54491bb74bdc2d09088b4567","_type":"Item"}