{"_id":"6567e7681265c8a131069b0f","_name":"scope_30mm_sig_tango6t_1_6x24","_parent":"55818ae44bdc2dde698b456c","_props":{"Name":"scope_30mm_sig_tango6t_1_6x24","ShortName":"scope_30mm_sig_tango6t_1_6x24","Description":"scope_30mm_sig_tango6t_1_6x24","Weight":0.626,"BackgroundColor":"blue","Width":2,"Height":1,"StackMaxSize":1,"ItemSound":"mod","Prefab":{"path":"assets/content/items/mods/scopes/scope_30mm_sig_tango6t_1_6x24.bundle","rcid":""},"UsePrefab":{"path":"","rcid":""},"StackObjectsCount":1,"NotShownInSlot":false,"ExaminedByDefault":true,"ExamineTime":0.25,"IsUndiscardable":false,"IsUnsaleable":false,"IsUnbuyable":false,"IsUngivable":false,"IsLockedafterEquip":false,"QuestItem":false,"LootExperience":30,"ExamineExperience":16,"HideEntrails":false,"RepairCost":0,"RepairSpeed":0,"ExtraSizeLeft":0,"ExtraSizeRight":0,"ExtraSizeUp":0,"ExtraSizeDown":0,"ExtraSizeForceAdd":false,"MergesWithChildren":true,"CanSellOnRagfair":true,"CanRequireOnRagfair":true,"ConflictingItems":["591c4efa86f7741030027726","570fd79bd2720bc7458b4583","570fd6c2d2720bc6458b457f","558022b54bdc2dac148b458d","58491f3324597764bc48fa02","584924ec24597768f12ae244","5b30b0dc5acfc400153b7124","60a23797a37c940de7062d02","5d2da1e948f035477b1ce2ba","5c0505e00db834001b735073","609a63b6e2ff132951242d09","584984812459776a704a82a6","59f9d81586f7744c7506ee62","570fd721d2720bc5458b4596","5c7d55f52e221644f31bff6a","6165ac8c290d254f5e6b2f6c","6477772ea8a38bb2050ed4db","64785e7c19d732620e045e15","all_vortex_uh1_black","all_553_usarmy","553_fullfde","all_okp7","all_valday_1p87_marks","scope_1p87_camo","scope_1p87_emr","scope_1p87_tan","eotech_coffe","razor_brown","sigs_fde","walther_fde","mod_c_eotechfde","010521_OPT_RAZOR_FDE0000","01005_EXPS3","gc_01012_VORTEX_RAZOR_UH1","gc_01014_EXPS3","SC_01042_VORTEX_RAZOR_UH1","CCG_SIGHT_TWO"],"Unlootable":false,"UnlootableFromSlot":"FirstPrimaryWeapon","UnlootableFromSide":[],"AnimationVariantsNumber":0,"DiscardingBlock":false,"RagFairCommissionModifier":1,"IsAlwaysAvailableForInsurance":false,"DiscardLimit":-1,"DropSoundType":"None","InsuranceDisabled":false,"QuestStashMaxCount":0,"IsSpecialSlotOnly":false,"IsUnremovable":false,"Grids":[],"Slots":[],"CanPutIntoDuringTheRaid":true,"CantRemoveFromSlotsDuringRaid":[],"Durability":100,"Accuracy":0,"Recoil":0,"Loudness":0,"EffectiveDistance":0,"Ergonomics":-4,"Velocity":0,"RaidModdable":true,"ToolModdable":true,"BlocksFolding":false,"BlocksCollapsible":false,"IsAnimated":false,"HasShoulderContact":false,"SightingRange":1500,"DoubleActionAccuracyPenaltyMult":1,"UniqueAnimationModID":0,"CustomAimPlane":"","sightModType":"optic","ScopesCount":1,"AimSensitivity":[[0.1,0.6]],"ModesCount":[2],"Zooms":[[6,1]],"CalibrationDistances":[[50,100,150,200,250,300]],"LevelRewardsItemLevel":1},"_type":"Item","_proto":"56ea70acd2720b844b8b4594"}