{"_id":"6452519e3d52156624001fd5","_name":"stock_vsk94_kbp_vsk94_std","_parent":"55818a594bdc2db9688b456a","_props":{"Name":"","ShortName":"","Description":"","Weight":0.7,"BackgroundColor":"blue","Width":2,"Height":1,"StackMaxSize":1,"ItemSound":"mod","Prefab":{"path":"assets/content/items/mods/stocks/stock_vsk94_kbp_vsk94_std.bundle","rcid":""},"UsePrefab":{"path":"","rcid":""},"StackObjectsCount":1,"NotShownInSlot":false,"ExaminedByDefault":true,"ExamineTime":0.25,"IsUndiscardable":false,"IsUnsaleable":false,"IsUnbuyable":false,"IsUngivable":false,"IsLockedafterEquip":false,"QuestItem":false,"LootExperience":20,"ExamineExperience":4,"HideEntrails":false,"RepairCost":0,"RepairSpeed":0,"ExtraSizeLeft":0,"ExtraSizeRight":1,"ExtraSizeUp":0,"ExtraSizeDown":1,"ExtraSizeForceAdd":false,"MergesWithChildren":true,"CanSellOnRagfair":true,"CanRequireOnRagfair":true,"ConflictingItems":[],"Unlootable":false,"UnlootableFromSlot":"FirstPrimaryWeapon","UnlootableFromSide":[],"AnimationVariantsNumber":0,"DiscardingBlock":false,"RagFairCommissionModifier":1,"IsAlwaysAvailableForInsurance":false,"DiscardLimit":-1,"DropSoundType":"None","InsuranceDisabled":false,"QuestStashMaxCount":0,"IsSpecialSlotOnly":false,"IsUnremovable":false,"Grids":[],"Slots":[],"CanPutIntoDuringTheRaid":true,"CantRemoveFromSlotsDuringRaid":[],"Durability":100,"Accuracy":0,"Recoil":-23,"Loudness":0,"EffectiveDistance":0,"Ergonomics":15,"Velocity":0,"RaidModdable":true,"ToolModdable":false,"BlocksFolding":false,"BlocksCollapsible":false,"IsAnimated":false,"HasShoulderContact":true,"SightingRange":0,"DoubleActionAccuracyPenaltyMult":1,"UniqueAnimationModID":0,"IsShoulderContact":false,"Foldable":false,"Retractable":false,"SizeReduceRight":0,"HeatFactor":1,"CoolFactor":1,"DurabilityBurnModificator":1,"LevelRewardsItemLevel":1},"_type":"Item","_proto":"57616ca52459773c69055192"}